pyprotostuben/__init__.py
pyprotostuben/codegen/__init__.py
pyprotostuben/codegen/abc.py
pyprotostuben/codegen/brokrpc/__init__.py
pyprotostuben/codegen/brokrpc/generator.py
pyprotostuben/codegen/brokrpc/plugin.py
pyprotostuben/codegen/echo.py
pyprotostuben/codegen/module_ast.py
pyprotostuben/codegen/mypy/__init__.py
pyprotostuben/codegen/mypy/builder.py
pyprotostuben/codegen/mypy/generator.py
pyprotostuben/codegen/mypy/model.py
pyprotostuben/codegen/mypy/plugin.py
pyprotostuben/codegen/run.py
pyprotostuben/logging.py
pyprotostuben/pool/__init__.py
pyprotostuben/pool/abc.py
pyprotostuben/pool/process.py
pyprotostuben/protobuf/__init__.py
pyprotostuben/protobuf/context.py
pyprotostuben/protobuf/extension.py
pyprotostuben/protobuf/file.py
pyprotostuben/protobuf/location.py
pyprotostuben/protobuf/parser.py
pyprotostuben/protobuf/registry.py
pyprotostuben/protobuf/visitor/__init__.py
pyprotostuben/protobuf/visitor/abc.py
pyprotostuben/protobuf/visitor/decorator.py
pyprotostuben/protobuf/visitor/model.py
pyprotostuben/protobuf/visitor/walker.py
pyprotostuben/protoc.py
pyprotostuben/py.typed
pyprotostuben/python/__init__.py
pyprotostuben/python/ast_builder.py
pyprotostuben/python/info.py
pyprotostuben/string_case.py
pyprotostuben-0.3.4.dist-info/LICENSE
pyprotostuben-0.3.4.dist-info/METADATA
pyprotostuben-0.3.4.dist-info/WHEEL
pyprotostuben-0.3.4.dist-info/entry_points.txt
pyprotostuben-0.3.4.dist-info/RECORD
