Metadata-Version: 2.3
Name: pyprotostuben
Version: 0.3.4
Summary: Generate Python MyPy stub modules from protobuf files.
License: MIT
Keywords: python,codegen,protobuf,grpc
Author: zerlok
Author-email: danil.troshnev@gmail.com
Requires-Python: >=3.9,<4.0
Classifier: Development Status :: 3 - Alpha
Classifier: Intended Audience :: Developers
Classifier: License :: OSI Approved :: MIT License
Classifier: Operating System :: OS Independent
Classifier: Programming Language :: Python :: 3
Classifier: Programming Language :: Python :: 3.9
Classifier: Programming Language :: Python :: 3.10
Classifier: Programming Language :: Python :: 3.11
Classifier: Programming Language :: Python :: 3.12
Classifier: Programming Language :: Python :: 3.13
Classifier: Topic :: Software Development :: Code Generators
Classifier: Typing :: Typed
Requires-Dist: protobuf (>=5.28.3,<6.0.0)
Project-URL: Homepage, https://github.com/zerlok/pyprotostuben
Project-URL: Issues, https://github.com/zerlok/pyprotostuben/issues
